1x3 router/router_fifo.v
module router_fifo(input clock,
    resetn,
    write_enb,
    soft_reset,
    read_enb,
    lfd_state,
    input [7:0] data_in,
    output empty,full,
    output reg [7:0] data_out);
    reg [8:0] mem [0:15];
    reg [4:0] wr_ptr,rd_ptr;
    reg [6:0] fifo_counter;
    reg lfd_tmp;
    integer i;
    // Logic for lfd_state
    always@(posedge clock)
        begin
            if(!resetn)
                lfd_tmp <= 0;
            else
                lfd_tmp <= lfd_state;
        end
    // Logic for read and write pointer
    always@(posedge clock)
        begin
            if(!resetn)
                begin
                    wr_ptr <= 0;
                    rd_ptr <= 0;
                end
            else if(soft_reset)
                begin
                    wr_ptr <= 0;
                    rd_ptr <= 0;
                end
            else
                begin
                    if(!full && write_enb)
                        wr_ptr <= wr_ptr + 1'b1;
                    if(!empty && read_enb)
                        rd_ptr <= rd_ptr + 1'b1;
                end
        end
    // Logic for FIFO counter
    always@(posedge clock)
        begin
            if(!resetn)
                fifo_counter <= 0;
            else if(soft_reset)
                fifo_counter <= 0;
            else if(read_enb && !empty)
                begin
                    if(mem[rd_ptr[3:0]][8] == 1'b1)
                        fifo_counter <= mem[rd_ptr[3:0]][7:2] + 1'b1;
                    else if(fifo_counter)
                        fifo_counter <= fifo_counter - 1'b1;
                end
        end
    // Logic for read operation
    always@(posedge clock)
        begin
            if(!resetn)
                data_out <= 0;
            else if(soft_reset)
                data_out <= 8'bz;
            else if(!fifo_counter && empty)
                data_out <= 8'bz;
            else if(read_enb && !empty)
                data_out <= mem[rd_ptr[3:0]][7:0];
        end
    // Logic for write operation
    always@(posedge clock)
        begin
            if(!resetn)
                for(i=0;i<16;i=i+1)
                    mem[i] <= 0;
            else if(soft_reset)
                for(i=0;i<16;i=i+1)
                    mem[i] <= 0;
            else if(write_enb && !full)
                mem[wr_ptr[3:0]] <= {lfd_tmp,data_in};
        end
    // Logic for empty and full
    assign empty = (wr_ptr==rd_ptr)?1'b1:1'b0;
    assign full = (wr_ptr=={~rd_ptr[4],rd_ptr[3:0]})?1'b1:1'b0;
endmodule

1x3 router/router_reg.v
module router_reg (input clock,
    resetn,
    pkt_valid,
    fifo_full,
    rst_int_reg,
    detect_add,
    ld_state,
    laf_state,
    full_state,
    lfd_state,
    input [7:0] data_in,
    output reg parity_done,
    low_pkt_valid,
    err,
    output reg [7:0] dout);
    reg [7:0] header_byte, fifo_full_state_byte, internal_parity, packet_parity;
    // Logic to store header byte and FIFO full state byte
    always@(posedge clock)
        begin
            if(!resetn)
                begin
                    header_byte <= 0;
                    fifo_full_state_byte <= 0;
                end
            else if(detect_add && pkt_valid)
                header_byte <= data_in;
            else if(ld_state && fifo_full)
                fifo_full_state_byte <= data_in;
        end
    // Logic for dout
    always@(posedge clock)
    begin
        if(!resetn)
            dout <= 0;
        else if(lfd_state)
            dout <= header_byte;
        else if(laf_state)
            dout <= fifo_full_state_byte;
        else if(ld_state && !fifo_full)
            dout <= data_in;
    end
    // Logic for parity_done
    always@(posedge clock)
    begin
        if(!resetn)
            parity_done <= 0;
        else if(detect_add)
            parity_done <= 0;
        else if((ld_state && !pkt_valid && !fifo_full) || (laf_state && low_pkt_valid && !parity_done))
            parity_done <= 1'b1;
    end
    // Logic for low_pkt_valid
    always@(posedge clock)
    begin
        if(!resetn)
            low_pkt_valid <= 0;
        else if(ld_state && !pkt_valid)
            low_pkt_valid <= 1'b1;
        else if(rst_int_reg)
            low_pkt_valid <= 0;
    end
    // Logic for internal_parity
    always@(posedge clock)
    begin
        if(!resetn)
            internal_parity <= 0;
        else if(detect_add)
            internal_parity <= 0;
        else if(lfd_state)
            internal_parity <= internal_parity ^ header_byte;
        else if(ld_state && pkt_valid && !full_state)
            internal_parity <= internal_parity ^ data_in;
    end
    // Logic for packet_parity
    always@(posedge clock)
    begin
        if(!resetn)
            packet_parity <= 0;
        else if((ld_state && !pkt_valid && !fifo_full) || (laf_state && low_pkt_valid && !parity_done))
            packet_parity <= data_in;
    end
    // Logic for err
    always@(posedge clock)
    begin
        if(!resetn)
            err <= 0;
        else if(parity_done && (internal_parity != packet_parity))
            err <= 1'b1;
        else
            err <= 0;
    end
endmodule

1x3 router/router_sync.v
module router_sync(input clock,
    resetn,
    detect_add,
    write_enb_reg,
    read_enb_0,
    read_enb_1,
    read_enb_2,
    empty_0,
    empty_1,
    empty_2,
    full_0,
    full_1,
    full_2,
    input [1:0] data_in,
    output reg fifo_full,
    soft_reset_0,
    soft_reset_1,
    soft_reset_2,
    output vld_out_0,
    vld_out_1,
    vld_out_2,
    output reg [2:0] write_enb);
    reg[1:0] fifo_addr;
    reg[4:0] timer_0,timer_1,timer_2;
    // Logic for storing address
    always@(posedge clock)
    begin
        if(!resetn)
            fifo_addr <= 0;
        else if(detect_add)
            fifo_addr <= data_in;
    end
    // Logic for fifo full status
    always@(*)
    begin
        if(!resetn)
            fifo_full = 0;
        else
            begin
                case(fifo_addr)
                2'b00 : fifo_full = full_0;
                2'b01 : fifo_full = full_1;
                2'b10 : fifo_full = full_2;
                default: fifo_full = 0;
                endcase
            end
    end
    // Logic for write enable
    always@(*)
    begin
        if(!resetn)
            write_enb = 0;
        else if(write_enb_reg)
            begin
                case(fifo_addr)
                2'b00 : write_enb = 3'b001;
                2'b01 : write_enb = 3'b010;
                2'b10 : write_enb = 3'b100;
                default : write_enb = 3'b0;
                endcase
            end
        else
            write_enb = 0;
    end
    // Logic for valid out signal
    assign vld_out_0 = ~empty_0;
    assign vld_out_1 = ~empty_1;
    assign vld_out_2 = ~empty_2;
    // Logic for soft reset 0
    always@(posedge clock)
    begin
        if(!resetn)
            begin
                soft_reset_0 <= 0;
                timer_0 <= 0;
            end
        else if(~vld_out_0)
            begin
                soft_reset_0 <= 0;
                timer_0 <= 0;
            end
        else if(read_enb_0)
            begin
                soft_reset_0 <= 0;
                timer_0 <= 0;
            end
        else
            begin
                if(timer_0 == 5'd29)
                    begin
                        soft_reset_0 <= 1'b1;
                        timer_0 <= 0;
                    end
                else
                    begin
                        timer_0 <= timer_0 + 1'b1;
                        soft_reset_0 <= 0;
                    end
            end
    end
    // Logic for soft reset 1
    always@(posedge clock)
    begin
        if(!resetn)
            begin
                soft_reset_1 <= 0;
                timer_1 <= 0;
            end
        else if(~vld_out_1)
            begin
                soft_reset_1 <= 0;
                timer_1 <= 0;
            end
        else if(read_enb_1)
            begin
                soft_reset_1 <= 0;
                timer_1 <= 0;
            end
        else
            begin
                if(timer_1 == 5'd29)
                    begin
                        soft_reset_1 <= 1'b1;
                        timer_1 <= 0;
                    end
                else
                    begin
                        timer_1 <= timer_1 + 1'b1;
                        soft_reset_1 <= 0;
                    end
            end
    end
    // Logic for soft reset 2
    always@(posedge clock)
        begin
            if(!resetn)
                begin
                    soft_reset_2 <= 0;
                    timer_2 <= 0;
                end
            else if(~vld_out_2)
                begin
                    soft_reset_2 <= 0;
                    timer_2 <= 0;
                end
            else if(read_enb_2)
                begin
                    soft_reset_2 <= 0;
                    timer_2 <= 0;
                end
            else
                begin
                    if(timer_2 == 5'd29)
                        begin
                            soft_reset_2 <= 1'b1;
                            timer_2 <= 0;
                        end
                    else
                        begin
                            timer_2 <= timer_2 + 1'b1;
                            soft_reset_2 <= 0;
                        end
                end
        end
endmodule

1x3 router/router_fsm.v
module router_fsm(input clock,
    resetn,
    pkt_valid,
    parity_done,
    soft_reset_0,
    soft_reset_1,
    soft_reset_2,
    fifo_full,
    low_pkt_valid,
    fifo_empty_0,
    fifo_empty_1,
    fifo_empty_2,
    input [1:0] data_in,
    output busy,
    detect_add,
    ld_state,
    laf_state,
    full_state,
    write_enb_reg,
    rst_int_reg,
    lfd_state);
    parameter DECODE_ADDRESS = 3'b000,LOAD_FIRST_DATA = 3'b001,LOAD_DATA = 3'b010,FIFO_FULL_STATE =3'b011,LOAD_AFTER_FULL = 3'b100,LOAD_PARITY = 3'b101,CHECK_PARITY_ERROR = 3'b110,WAIT_TILL_EMPTY = 3'b111;
    reg [1:0] addr;
    reg [2:0] present_state, next_state;
    // Present State Logic
    always@(posedge clock)
    begin
        if(!resetn)
            present_state <= DECODE_ADDRESS;
        else if((soft_reset_0 && data_in == 2'b00)|| (soft_reset_1 && data_in == 2'b01) || (soft_reset_2 && data_in == 2'b10))
            present_state <= DECODE_ADDRESS;
        else
            present_state <= next_state;
    end
    // Logic for storing the address
    always@(posedge clock)
    begin
        if(!resetn)
            addr <= 0;
        else if((soft_reset_0 && data_in == 2'b00)|| (soft_reset_1 && data_in == 2'b01) || (soft_reset_2 && data_in == 2'b10))
            addr <= 0;
        if(present_state == DECODE_ADDRESS && data_in!= 2'b11)
            addr <= data_in;
    end
    // Next State Logic
    always@(*)
    begin
        if(addr != 2'b11)
        begin
            next_state = DECODE_ADDRESS;
            case(present_state)
            DECODE_ADDRESS: begin
                if((pkt_valid && (data_in[1:0]==0) && fifo_empty_0) || (pkt_valid && (data_in[1:0]==1) && fifo_empty_1) || (pkt_valid && (data_in[1:0]==2) && fifo_empty_2))
                    next_state = LOAD_FIRST_DATA;
                else if((pkt_valid && (data_in[1:0]==0) && !fifo_empty_0) || (pkt_valid && (data_in[1:0]==1) && !fifo_empty_1) || (pkt_valid && (data_in[1:0]==2) && !fifo_empty_2))
                    next_state = WAIT_TILL_EMPTY;
            end
            LOAD_FIRST_DATA: next_state = LOAD_DATA;
            LOAD_DATA: begin
                if(fifo_full)
                    next_state = FIFO_FULL_STATE;
                else if(!fifo_full && !pkt_valid)
                    next_state = LOAD_PARITY;
                else
                    next_state = LOAD_DATA;
            end
            FIFO_FULL_STATE: begin
                if(!fifo_full)
                    next_state = LOAD_AFTER_FULL;
                else
                    next_state = FIFO_FULL_STATE;
            end
            LOAD_AFTER_FULL: begin
                if(!parity_done && !low_pkt_valid)
                    next_state = LOAD_DATA;
                else if(!parity_done && low_pkt_valid)
                    next_state = LOAD_PARITY;
                else if(parity_done)
                    next_state = DECODE_ADDRESS;
            end
            LOAD_PARITY : next_state = CHECK_PARITY_ERROR;
            CHECK_PARITY_ERROR: begin 
                if(fifo_full)
                    next_state = FIFO_FULL_STATE;
                else if(!fifo_full)
                    next_state = DECODE_ADDRESS;
            end
            WAIT_TILL_EMPTY: begin
                if((fifo_empty_0 && (addr == 0)) || (fifo_empty_1 && (addr == 1)) || (fifo_empty_2 && (addr == 2)))
                    next_state = LOAD_FIRST_DATA;
                else
                    next_state = WAIT_TILL_EMPTY;
            end
            default : next_state = DECODE_ADDRESS;        
        endcase
        end
        else
            next_state = DECODE_ADDRESS;
    end
    // Logic for output logic
    assign detect_add = (present_state == DECODE_ADDRESS) ? 1'b1 : 1'b0;
    assign ld_state = (present_state == LOAD_DATA) ? 1'b1 : 1'b0;
    assign lfd_state = (present_state == LOAD_FIRST_DATA) ? 1'b1 : 1'b0;
    assign laf_state = (present_state == LOAD_AFTER_FULL) ? 1'b1 : 1'b0;
    assign full_state = (present_state == FIFO_FULL_STATE) ? 1'b1 : 1'b0;
    assign write_enb_reg = ((present_state == LOAD_DATA) || (present_state == LOAD_AFTER_FULL) | (present_state == LOAD_PARITY)) ? 1'b1 : 1'b0;
    assign rst_int_reg = (present_state == CHECK_PARITY_ERROR) ? 1'b1 : 1'b0;
    assign busy = ((present_state == LOAD_DATA) || (present_state == DECODE_ADDRESS)) ? 1'b0 : 1'b1;
endmodule

1x3 router/router_top.v
`include "router_fifo.v"
`include "router_fsm.v"
`include "router_sync.v"
`include "router_reg.v"

module router_top(input clock,
    resetn,
    read_enb_0,
    read_enb_1,
    read_enb_2,
    pkt_valid,
    input [7:0] data_in,
    output vld_out_0,
    vld_out_1,
    vld_out_2,
    err,
    busy,
    output [7:0] data_out_0,
    data_out_1,
    data_out_2);
    wire [2:0] write_enb;
    wire [7:0] dout;
    wire parity_done,soft_reset_0,soft_reset_1,soft_reset_2,fifo_full,low_pkt_valid,detect_add,ld_state,laf_state,full_state,write_enb_reg,rst_int_reg,lfd_state,empty_0,empty_1,empty_2,full_0,full_1,full_2;
    router_fsm FSM(clock,resetn,pkt_valid,parity_done,soft_reset_0,soft_reset_1,soft_reset_2,fifo_full,low_pkt_valid,empty_0,empty_1,empty_2,data_in[1:0],busy,detect_add,ld_state,laf_state,full_state,write_enb_reg,rst_int_reg,lfd_state);
    router_sync Synchronizer(clock,resetn,detect_add,write_enb_reg,read_enb_0,read_enb_1,read_enb_2,empty_0,empty_1,empty_2,full_0,full_1,full_2,data_in[1:0],fifo_full,soft_reset_0,soft_reset_1,soft_reset_2,vld_out_0,vld_out_1,vld_out_2,write_enb);
    router_reg Register(clock,resetn,pkt_valid,fifo_full,rst_int_reg,detect_add,ld_state,laf_state,full_state,lfd_state,data_in,parity_done,low_pkt_valid,err,dout);
    router_fifo FIFO_0(clock,resetn,write_enb[0],soft_reset_0,read_enb_0,lfd_state,dout,empty_0,full_0,data_out_0);
    router_fifo FIFO_1(clock,resetn,write_enb[1],soft_reset_1,read_enb_1,lfd_state,dout,empty_1,full_1,data_out_1);
    router_fifo FIFO_2(clock,resetn,write_enb[2],soft_reset_2,read_enb_2,lfd_state,dout,empty_2,full_2,data_out_2);
endmodule

1x3 router/testBench.v
module router_top_tb();
    reg clock,resetn,read_enb_0,read_enb_1,read_enb_2,pkt_valid;
    reg [7:0] data_in;
    wire vld_out_0,vld_out_1,vld_out_2,err,busy;
    wire [7:0] data_out_0,data_out_1,data_out_2;
    event e1,e2;
    parameter T = 10;
    router_top DUT(clock,
        resetn,
        read_enb_0,
        read_enb_1,
        read_enb_2,
        pkt_valid,
        data_in,
        vld_out_0,
        vld_out_1,
        vld_out_2,
        err,
        busy,
        data_out_0,
        data_out_1,
        data_out_2);
    initial
        begin
            clock = 1'b0;
            forever #(T/2) clock = ~clock;
        end
    task initialize;
        begin
            resetn = 1'b1;
            read_enb_0 = 0;
            read_enb_1 = 0;
            read_enb_2 = 0;
            pkt_valid = 0;
            data_in = 0;
        end
    endtask
    task reset_ip;
        begin
            @(negedge clock);
            resetn = 1'b0;
            @(negedge clock);
            resetn = 1'b1;
        end
    endtask
    task payload_14_15(input [5:0]d1,input [1:0]a1);
        reg [7:0] header, payload, parity;
        reg [5:0] payload_len;
        reg [1:0] addr;
        integer i;
        begin
            @(negedge clock);
            wait(!busy)
            @(negedge clock);
            parity = 0;
            payload_len = d1;
            addr = a1;
            header = {payload_len,addr};
            parity = parity ^ header;
            pkt_valid = 1'b1;
            data_in = header;
            @(negedge clock);
            wait(!busy)
            for(i=0;i<payload_len;i=i+1)begin
                @(negedge clock);
                wait(!busy)
                payload = i;
                parity = parity ^ payload;
                data_in = payload;
            end 
            wait(!busy)
            @(negedge clock);
            pkt_valid = 0;
            data_in = parity;
        end
    endtask   
    task payload_16_17(input [5:0]d2,input [1:0]a2);
        reg [7:0] header, payload, parity;
        reg [5:0] payload_len;
        reg [1:0] addr;
        integer i;
        begin
            @(negedge clock);
            wait(!busy)
            parity = 0;
            payload_len = d2;
            addr = a2;
            header = {payload_len,addr};
            parity = parity ^ header;
            @(negedge clock);
            pkt_valid = 1'b1;
            data_in = header;
            @(negedge clock);
            wait(!busy)
            for(i=0;i<payload_len;i=i+1)
                begin
                @(negedge clock);
                wait(!busy)
                payload = i;
                parity = parity ^ payload;
                data_in = payload;
                end
            ->e1;
            wait(!busy)
            @(negedge clock);
            pkt_valid = 0;
            data_in = parity;
        end
    endtask
    task random_packet(input [5:0]d3,input [1:0]a3);
        reg [7:0] header, payload, parity;
        reg [5:0] payload_len;
        reg [1:0] addr;
        integer i;
        begin
            ->e2;
            @(negedge clock);
            wait(!busy)
            parity = 0;
            payload_len = d3;
            addr = a3;
            header = {payload_len,addr};
            parity = parity ^ header;
            @(negedge clock);
            pkt_valid = 1'b1;
            data_in = header;
            @(negedge clock);
            wait(!busy)
            for(i=0;i<payload_len;i=i+1)begin
                @(negedge clock);
                wait(!busy) 
                payload= i;
                parity = parity ^ payload;
                data_in = payload;
            end 
            wait(!busy)
            @(negedge clock);
            pkt_valid = 0;
            data_in = parity;
        end
    endtask
    
    initial
        begin
            forever
                begin
                    @(e1)
                    begin
                        @(negedge clock);
                        read_enb_1 = 1'b1;
                        wait(!vld_out_1)
                        @(negedge clock);
                        read_enb_1 = 0;
                    end
                end
        end
    initial
        begin
            forever
                begin
                    @(e2)
                    begin
                        wait(vld_out_2)
                        @(negedge clock);
                        read_enb_2 = 1'b1;
                        wait(!vld_out_2)
                        @(negedge clock);
                        read_enb_2 = 0;
                    end
                end
        end
    initial
        begin
            initialize;
            reset_ip;
            repeat (2) @(negedge clock);
            // Packet Size = 16bytes
            // DA-LFD-LD-LP-CPE-DA
            // payload_14_15(6'd14,2'd0);
            // @(negedge clock);
            // read_enb_0 = 1'b1;
            // wait(!vld_out_0)
            // @(negedge clock);
            // read_enb_0 = 0;
            // #100;
            // Packet Size = 17bytes
            // DA-LFD-LD-LP-CPE-FFS-LAF-DA
            payload_14_15(6'd17,2'd0);
            @(negedge clock);
            wait(busy)
            @(negedge clock);
            read_enb_0 = 1'b1;
            wait(!vld_out_0)
            @(negedge clock);
            read_enb_0 = 0;
            #100;
            // Packet Size = 18bytes
            // DA-LFD-LD-FFS-LAF-LP-CPE-DA
            // payload_16_17(6'd16,2'd1);
            // wait(!vld_out_1)
            // @(negedge clock);
            // read_enb_1 = 0;
            // #100;
            // // Packet Size = 19bytes
            // // DA-LFD-LD-FFS-LAF-LD-LP-CPE-DA
            // payload_16_17(6'd17,2'd1);
            // wait(!vld_out_1)
            // @(negedge clock);
            // read_enb_1 = 0;
            // #100;
            // // Packet Size = 24bytes
            // // DA-LFD-LD-LP-CPE-DA
            // random_packet(6'd22,2'd2);
            // wait(!vld_out_2)
            // @(negedge clock);
            // read_enb_2 = 0;           
            // #100;
            $finish;
        end

    initial begin 
        $dumpfile("dump.vcd"); 
        $dumpvars(0,router_top_tb);
        $monitor("Data Input = %d, data_out_0 = %d, data_out_1 = %d, data_out_2 = %d,Busy = %b, Error = %b",data_in,data_out_0,data_out_1,data_out_2,busy,err);
    end
        
endmodule

1x3 router/dump.vcd
$date
	Sun Aug 13 14:14:51 2023
$end
$version
	Icarus Verilog
$end
$timescale
	1s
$end
$scope module router_top_tb $end
$var event 1 ! e2 $end
$var event 1 " e1 $end
$var wire 1 # vld_out_2 $end
$var wire 1 $ vld_out_1 $end
$var wire 1 % vld_out_0 $end
$var wire 1 & err $end
$var wire 8 ' data_out_2 [7:0] $end
$var wire 8 ( data_out_1 [7:0] $end
$var wire 8 ) data_out_0 [7:0] $end
$var wire 1 * busy $end
$var parameter 32 + T $end
$var reg 1 , clock $end
$var reg 8 - data_in [7:0] $end
$var reg 1 . pkt_valid $end
$var reg 1 / read_enb_0 $end
$var reg 1 0 read_enb_1 $end
$var reg 1 1 read_enb_2 $end
$var reg 1 2 resetn $end
$scope module DUT $end
$var wire 1 , clock $end
$var wire 8 3 data_in [7:0] $end
$var wire 1 . pkt_valid $end
$var wire 1 / read_enb_0 $end
$var wire 1 0 read_enb_1 $end
$var wire 1 1 read_enb_2 $end
$var wire 1 2 resetn $end
$var wire 1 4 write_enb_reg $end
$var wire 3 5 write_enb [2:0] $end
$var wire 1 # vld_out_2 $end
$var wire 1 $ vld_out_1 $end
$var wire 1 % vld_out_0 $end
$var wire 1 6 soft_reset_2 $end
$var wire 1 7 soft_reset_1 $end
$var wire 1 8 soft_reset_0 $end
$var wire 1 9 rst_int_reg $end
$var wire 1 : parity_done $end
$var wire 1 ; low_pkt_valid $end
$var wire 1 < lfd_state $end
$var wire 1 = ld_state $end
$var wire 1 > laf_state $end
$var wire 1 ? full_state $end
$var wire 1 @ full_2 $end
$var wire 1 A full_1 $end
$var wire 1 B full_0 $end
$var wire 1 C fifo_full $end
$var wire 1 & err $end
$var wire 1 D empty_2 $end
$var wire 1 E empty_1 $end
$var wire 1 F empty_0 $end
$var wire 8 G dout [7:0] $end
$var wire 1 H detect_add $end
$var wire 8 I data_out_2 [7:0] $end
$var wire 8 J data_out_1 [7:0] $end
$var wire 8 K data_out_0 [7:0] $end
$var wire 1 * busy $end
$scope module FIFO_0 $end
$var wire 1 , clock $end
$var wire 1 / read_enb $end
$var wire 1 2 resetn $end
$var wire 1 L write_enb $end
$var wire 1 8 soft_reset $end
$var wire 1 < lfd_state $end
$var wire 1 B full $end
$var wire 1 F empty $end
$var wire 8 M data_in [7:0] $end
$var reg 8 N data_out [7:0] $end
$var reg 7 O fifo_counter [6:0] $end
$var reg 1 P lfd_tmp $end
$var reg 5 Q rd_ptr [4:0] $end
$var reg 5 R wr_ptr [4:0] $end
$var integer 32 S i [31:0] $end
$upscope $end
$scope module FIFO_1 $end
$var wire 1 , clock $end
$var wire 1 0 read_enb $end
$var wire 1 2 resetn $end
$var wire 1 T write_enb $end
$var wire 1 7 soft_reset $end
$var wire 1 < lfd_state $end
$var wire 1 A full $end
$var wire 1 E empty $end
$var wire 8 U data_in [7:0] $end
$var reg 8 V data_out [7:0] $end
$var reg 7 W fifo_counter [6:0] $end
$var reg 1 X lfd_tmp $end
$var reg 5 Y rd_ptr [4:0] $end
$var reg 5 Z wr_ptr [4:0] $end
$var integer 32 [ i [31:0] $end
$upscope $end
$scope module FIFO_2 $end
$var wire 1 , clock $end
$var wire 1 1 read_enb $end
$var wire 1 2 resetn $end
$var wire 1 \ write_enb $end
$var wire 1 6 soft_reset $end
$var wire 1 < lfd_state $end
$var wire 1 @ full $end
$var wire 1 D empty $end
$var wire 8 ] data_in [7:0] $end
$var reg 8 ^ data_out [7:0] $end
$var reg 7 _ fifo_counter [6:0] $end
$var reg 1 ` lfd_tmp $end
$var reg 5 a rd_ptr [4:0] $end
$var reg 5 b wr_ptr [4:0] $end
$var integer 32 c i [31:0] $end
$upscope $end
$scope module FSM $end
$var wire 1 , clock $end
$var wire 2 d data_in [1:0] $end
$var wire 1 F fifo_empty_0 $end
$var wire 1 E fifo_empty_1 $end
$var wire 1 D fifo_empty_2 $end
$var wire 1 . pkt_valid $end
$var wire 1 2 resetn $end
$var wire 1 4 write_enb_reg $end
$var wire 1 6 soft_reset_2 $end
$var wire 1 7 soft_reset_1 $end
$var wire 1 8 soft_reset_0 $end
$var wire 1 9 rst_int_reg $end
$var wire 1 : parity_done $end
$var wire 1 ; low_pkt_valid $end
$var wire 1 < lfd_state $end
$var wire 1 = ld_state $end
$var wire 1 > laf_state $end
$var wire 1 ? full_state $end
$var wire 1 C fifo_full $end
$var wire 1 H detect_add $end
$var wire 1 * busy $end
$var parameter 3 e CHECK_PARITY_ERROR $end
$var parameter 3 f DECODE_ADDRESS $end
$var parameter 3 g FIFO_FULL_STATE $end
$var parameter 3 h LOAD_AFTER_FULL $end
$var parameter 3 i LOAD_DATA $end
$var parameter 3 j LOAD_FIRST_DATA $end
$var parameter 3 k LOAD_PARITY $end
$var parameter 3 l WAIT_TILL_EMPTY $end
$var reg 2 m addr [1:0] $end
$var reg 3 n next_state [2:0] $end
$var reg 3 o present_state [2:0] $end
$upscope $end
$scope module Register $end
$var wire 1 , clock $end
$var wire 8 p data_in [7:0] $end
$var wire 1 H detect_add $end
$var wire 1 ? full_state $end
$var wire 1 > laf_state $end
$var wire 1 = ld_state $end
$var wire 1 < lfd_state $end
$var wire 1 . pkt_valid $end
$var wire 1 2 resetn $end
$var wire 1 9 rst_int_reg $end
$var wire 1 C fifo_full $end
$var reg 8 q dout [7:0] $end
$var reg 1 & err $end
$var reg 8 r fifo_full_state_byte [7:0] $end
$var reg 8 s header_byte [7:0] $end
$var reg 8 t internal_parity [7:0] $end
$var reg 1 ; low_pkt_valid $end
$var reg 8 u packet_parity [7:0] $end
$var reg 1 : parity_done $end
$upscope $end
$scope module Synchronizer $end
$var wire 1 , clock $end
$var wire 2 v data_in [1:0] $end
$var wire 1 H detect_add $end
$var wire 1 F empty_0 $end
$var wire 1 E empty_1 $end
$var wire 1 D empty_2 $end
$var wire 1 B full_0 $end
$var wire 1 A full_1 $end
$var wire 1 @ full_2 $end
$var wire 1 / read_enb_0 $end
$var wire 1 0 read_enb_1 $end
$var wire 1 1 read_enb_2 $end
$var wire 1 2 resetn $end
$var wire 1 % vld_out_0 $end
$var wire 1 $ vld_out_1 $end
$var wire 1 # vld_out_2 $end
$var wire 1 4 write_enb_reg $end
$var reg 2 w fifo_addr [1:0] $end
$var reg 1 C fifo_full $end
$var reg 1 8 soft_reset_0 $end
$var reg 1 7 soft_reset_1 $end
$var reg 1 6 soft_reset_2 $end
$var reg 5 x timer_0 [4:0] $end
$var reg 5 y timer_1 [4:0] $end
$var reg 5 z timer_2 [4:0] $end
$var reg 3 { write_enb [2:0] $end
$upscope $end
$upscope $end
$scope task initialize $end
$upscope $end
$scope task payload_14_15 $end
$var reg 2 | a1 [1:0] $end
$var reg 2 } addr [1:0] $end
$var reg 6 ~ d1 [5:0] $end
$var reg 8 !" header [7:0] $end
$var reg 8 "" parity [7:0] $end
$var reg 8 #" payload [7:0] $end
$var reg 6 $" payload_len [5:0] $end
$var integer 32 %" i [31:0] $end
$upscope $end
$scope task payload_16_17 $end
$var reg 2 &" a2 [1:0] $end
$var reg 2 '" addr [1:0] $end
$var reg 6 (" d2 [5:0] $end
$var reg 8 )" header [7:0] $end
$var reg 8 *" parity [7:0] $end
$var reg 8 +" payload [7:0] $end
$var reg 6 ," payload_len [5:0] $end
$var integer 32 -" i [31:0] $end
$upscope $end
$scope task random_packet $end
$var reg 2 ." a3 [1:0] $end
$var reg 2 /" addr [1:0] $end
$var reg 6 0" d3 [5:0] $end
$var reg 8 1" header [7:0] $end
$var reg 8 2" parity [7:0] $end
$var reg 8 3" payload [7:0] $end
$var reg 6 4" payload_len [5:0] $end
$var integer 32 5" i [31:0] $end
$upscope $end
$scope task reset_ip $end
$upscope $end
$upscope $end
$enddefinitions $end
$comment Show the parameter values. $end
$dumpall
b111 l
b101 k
b1 j
b10 i
b100 h
b11 g
b0 f
b110 e
b1010 +
$end
#0
$dumpvars
bx 5"
bx 4"
bx 3"
bx 2"
bx 1"
bx 0"
bx /"
bx ."
bx -"
bx ,"
bx +"
bx *"
bx )"
bx ("
bx '"
bx &"
bx %"
bx $"
bx #"
bx ""
bx !"
bx ~
bx }
bx |
b0 {
bx z
bx y
bx x
bx w
b0 v
bx u
bx t
bx s
bx r
bx q
b0 p
bx o
b0 n
bx m
b0 d
bx c
bx b
bx a
x`
bx _
bx ^
bx ]
0\
bx [
bx Z
bx Y
xX
bx W
bx V
bx U
0T
bx S
bx R
bx Q
xP
bx O
bx N
bx M
0L
bx K
bx J
bx I
xH
bx G
xF
xE
xD
0C
xB
xA
x@
x?
x>
x=
x<
x;
x:
x9
x8
x7
x6
b0 5
x4
b0 3
12
01
00
0/
0.
b0 -
0,
x*
bx )
bx (
bx '
x&
x%
x$
x#
1"
1!
$end
#5
04
0*
1H
0=
0<
0>
0?
09
b0 o
08
07
06
0&
1,
#10
02
0,
#15
0@
0A
0B
0#
0$
0%
1D
1E
1F
b0 '
b0 I
b0 ^
b0 _
b0 a
b0 b
0`
b0 (
b0 J
b0 V
b0 W
b0 Y
b0 Z
0X
b0 )
b0 K
b0 N
b0 O
b0 Q
b0 R
0P
b0 u
b0 t
0;
0:
b0 G
b0 M
b0 U
b0 ]
b0 q
b0 r
b0 s
b0 z
b0 y
b0 x
b0 w
b0 m
b10000 c
b10000 [
b10000 S
1,
#20
12
0,
#25
bz )
bz K
bz N
bz (
bz J
bz V
bz '
bz I
bz ^
1,
#30
0,
#35
1,
#40
b0 |
b10001 ~
0,
#45
1,
#50
0,
#55
1,
#60
b1 n
b1000100 -
b1000100 3
b1000100 p
1.
b1000100 !"
b0 }
b10001 $"
b1000100 ""
0,
#65
1*
b10 n
0H
1<
b1 o
b1000100 s
1,
#70
0,
#75
1L
b1 5
b1 {
b0 %"
14
0*
b10 n
1=
0<
1`
1X
1P
b1000100 t
b1000100 G
b1000100 M
b1000100 U
b1000100 ]
b1000100 q
b10 o
1,
#80
b1 %"
b0 -
b0 3
b0 p
b0 #"
0,
#85
1%
b10 n
0F
b0 G
b0 M
b0 U
b0 ]
b0 q
0P
b1 R
0X
0`
1,
#90
b10 n
b1 d
b1 v
b10 %"
b1 -
b1 3
b1 p
b1000101 ""
b1 #"
0,
#95
b10 R
b1000101 t
b1 G
b1 M
b1 U
b1 ]
b1 q
b1 x
1,
#100
b10 n
b10 d
b10 v
b11 %"
b10 -
b10 3
b10 p
b1000111 ""
b10 #"
0,
#105
b10 x
b10 G
b10 M
b10 U
b10 ]
b10 q
b1000111 t
b11 R
1,
#110
b10 n
b11 d
b11 v
b100 %"
b11 -
b11 3
b11 p
b1000100 ""
b11 #"
0,
#115
b100 R
b1000100 t
b11 G
b11 M
b11 U
b11 ]
b11 q
b11 x
1,
#120
b10 n
b0 d
b0 v
b101 %"
b100 -
b100 3
b100 p
b1000000 ""
b100 #"
0,
#125
b100 x
b100 G
b100 M
b100 U
b100 ]
b100 q
b1000000 t
b101 R
1,
#130
b10 n
b1 d
b1 v
b110 %"
b101 -
b101 3
b101 p
b1000101 ""
b101 #"
0,
#135
b110 R
b1000101 t
b101 G
b101 M
b101 U
b101 ]
b101 q
b101 x
1,
#140
b10 n
b10 d
b10 v
b111 %"
b110 -
b110 3
b110 p
b1000011 ""
b110 #"
0,
#145
b110 x
b110 G
b110 M
b110 U
b110 ]
b110 q
b1000011 t
b111 R
1,
#150
b10 n
b11 d
b11 v
b1000 %"
b111 -
b111 3
b111 p
b1000100 ""
b111 #"
0,
#155
b1000 R
b1000100 t
b111 G
b111 M
b111 U
b111 ]
b111 q
b111 x
1,
#160
b10 n
b0 d
b0 v
b1001 %"
b1000 -
b1000 3
b1000 p
b1001100 ""
b1000 #"
0,
